meshctl/__init__.py
meshctl/__main__.py
meshctl/cli.py
meshctl/connection.py
meshctl/discover.py
meshctl/list_nodes.py
meshctl/ping.py
meshctl/scan_ble.py
meshctl/traceroute.py
meshctl-0.1.7.dist-info/METADATA
meshctl-0.1.7.dist-info/WHEEL
meshctl-0.1.7.dist-info/entry_points.txt
meshctl-0.1.7.dist-info/RECORD
