Metadata-Version: 2.4
Name: meshctl
Version: 0.1.7
Summary: A CLI tool for meshtastic operations
Project-URL: Homepage, https://github.com/mangelajo/meshctl
Project-URL: Repository, https://github.com/mangelajo/meshctl
Author-email: Miguel Angel Ajo Pelayo <miguelangel@ajo.es>
Requires-Python: >=3.8
Requires-Dist: click>=8.0.0
Requires-Dist: meshtastic>=2.3.14
Requires-Dist: rich>=13.0.0
